[
  {
    "model": "kpi.asset",
    "pk": 3,
    "parent": 3,
    "fields": {
      "name": "fixture asset with settings and qa",
      "content": {
        "survey": [
          {
            "type": "text",
            "label": "settings fixture q1",
            "name": "settings_fixture_q1",
            "kuid": "abc"
          },
          {
            "type": "text",
            "label": "settings fixture q2",
            "name": "settings_fixture_q2",
            "kuid": "def"
          }
        ]
      },
      "settings": {
        "description": "Description",
        "country": [
          {
            "label": "United States",
            "value": "USA"
          }
        ],
        "sector": {
          "label": "Education",
          "value": "Education"
        },
        "country_codes": ["USA"],
        "organization": "An organization"
      },
      "data_sharing": {
        "fields": [],
        "enabled": false
      },
      "date_created": "2022-04-05T21:00:22.402Z",
      "date_modified": "2022-04-05T21:00:33.946Z",
      "owner": 1,
      "uid": "aNp9yMt4zKpUtTeZUnozYG"
    }
  },
  {
    "model": "subsequences.QuestionAdvancedFeature",
    "pk": "qafmanualqual",
    "fields": {
      "question_xpath": "q1",
      "asset": 3,
      "action": "manual_qual",
      "params": [
        {
          "type": "qualInteger",
          "uuid": "a94c2b17-5f6e-4d88-8b31-2e9a7c6f54d0",
          "labels": {
            "_default": "How many characters appear in the story?"
          }
        },
        {
          "type": "qualSelectMultiple",
          "uuid": "b1f8c6a9-2d4e-4a73-8c5f-9e0b6d1a2374",
          "labels": {
            "_default": "What themes were present in the story?"
          },
          "choices": [
            {
              "uuid": "c4a9e2d1-7b6f-4a83-9d5e-1f8c3b2a0647",
              "labels": {
                "_default": "Empathy"
              }
            },
            {
              "uuid": "c4a9e2d1-7b6f-4a83-9d5e-1f8c3b2a0647",
              "labels": {
                "_default": "Apathy"
              }
            }
          ]
        },
        {
          "type": "qualSelectOne",
          "uuid": "6d8e4a1f-3b92-4c7a-9f61-0e5c2b7a8d43",
          "labels": {
            "_default": "Was this a first-hand account?"
          },
          "choices": [
            {
              "uuid": "6d8e4a1f-3b92-4c7a-9f61-0e5c2b7a8d43",
              "labels": {
                "_default": "Yes"
              }
            },
            {
              "uuid": "b1f8c6a9-2d4e-4a73-8c5f-9e0b6d1a2374",
              "labels": {
                "_default": "No"
              }
            }
          ]
        },
        {
          "type": "qualText",
          "uuid": "3f2a1d6c-8e7b-4f2d-9a1c-6b9e4d8f21a3",
          "labels": {
            "_default": "Add any further remarks"
          }
        }
      ]
    }
  },
  {
    "model": "subsequences.QuestionAdvancedFeature",
    "pk": "qafbedrockqual",
    "fields": {
      "question_xpath": "q1",
      "asset": 3,
      "action": "automatic_bedrock_qual",
      "params": [
        {
          "uuid": "a94c2b17-5f6e-4d88-8b31-2e9a7c6f54d0"
        },
        {
          "uuid": "b1f8c6a9-2d4e-4a73-8c5f-9e0b6d1a2374"
        },
        {
          "uuid": "6d8e4a1f-3b92-4c7a-9f61-0e5c2b7a8d43"
        },
        {
          "uuid": "3f2a1d6c-8e7b-4f2d-9a1c-6b9e4d8f21a3"
        }
      ]
    }
  },
  {
    "model": "subsequences.QuestionAdvancedFeature",
    "pk": "qaf678910",
    "fields": {
      "question_xpath": "q1",
      "asset": 3,
      "action": "manual_transcription",
      "params": [
        {
          "language": "en"
        }
      ]
    }
  },
  {
    "model": "subsequences.QuestionAdvancedFeature",
    "pk": "qaf111213",
    "fields": {
      "question_xpath": "q2",
      "asset": 3,
      "action": "manual_qual",
      "params": [
        {
          "type": "qualInteger",
          "uuid": "a94c2b17-5f6e-4d88-8b31-2e9a7c6f54d0",
          "labels": {
            "_default": "How many horses do they own?"
          }
        }
      ]
    }
  },
  {
    "model": "subsequences.QuestionAdvancedFeature",
    "pk": "qaf141516",
    "fields": {
      "question_xpath": "q2",
      "asset": 3,
      "action": "manual_transcription",
      "params": [
        {
          "language": "en"
        }
      ]
    }
  }
]
